oneroll-1.3.4.dist-info/METADATA
oneroll-1.3.4.dist-info/WHEEL
oneroll-1.3.4.dist-info/entry_points.txt
oneroll-1.3.4.dist-info/licenses/LICENSE
oneroll/__init__.py
oneroll/__main__.py
oneroll/_core.cpython-313t-powerpc64le-linux-gnu.so
oneroll/_core.pyi
oneroll/grammar.pest
oneroll/tui.py
oneroll-1.3.4.dist-info/RECORD
